koyomin/__init__.py
koyomin/callbacks/server.py
koyomin/core/interfaces/auth.py
koyomin/core/interfaces/subscriber.py
koyomin/core/interfaces/user.py
koyomin/core/utils/get_oauth_config.py
koyomin/core/utils/pubsub.py
koyomin/entities/user.py
koyomin/entrypoint/__init__.py
koyomin-1.0.1.dist-info/METADATA
koyomin-1.0.1.dist-info/WHEEL
koyomin-1.0.1.dist-info/RECORD
